plugins/starzai_memu/__init__.py
plugins/starzai_memu/config.py
NoneBot_Dev-0.1.0.dist-info/METADATA
NoneBot_Dev-0.1.0.dist-info/WHEEL
NoneBot_Dev-0.1.0.dist-info/top_level.txt
NoneBot_Dev-0.1.0.dist-info/RECORD
