Metadata-Version: 2.1
Name: NoneBot-Dev
Version: 0.1.0
Summary: NoneBot-Dev
Requires-Python: <4.0,>=3.8
